MANIFEST.in
distribute_setup.py
setup.py
docs/Makefile
waskr/__init__.py
waskr/config.py
waskr/database.py
waskr/log.py
waskr/main.py
waskr/middleware.py
waskr/plugins.py
waskr/util.py
waskr/waskrc.py
waskr.egg-info/PKG-INFO
waskr.egg-info/SOURCES.txt
waskr.egg-info/dependency_links.txt
waskr.egg-info/entry_points.txt
waskr.egg-info/requires.txt
waskr.egg-info/top_level.txt
waskr/tests/.coverage
waskr/tests/app.py
waskr/tests/mock.py
waskr/tests/test_configurations.py
waskr/tests/test_database.py
waskr/tests/test_dependencies.py
waskr/tests/test_imports.py
waskr/tests/test_init.py
waskr/tests/test_log.py
waskr/tests/test_plugins.py
waskr/tests/test_request_stats.py
waskr/tests/test_util.py
waskr/web/static/__init__.py
waskr/web/static/favicon.ico
waskr/web/static/logo.png
waskr/web/static/style.css
waskr/web/static/waskr.png
waskr/web/static/flot/API.txt
waskr/web/static/flot/FAQ.txt
waskr/web/static/flot/LICENSE.txt
waskr/web/static/flot/Makefile
waskr/web/static/flot/NEWS.txt
waskr/web/static/flot/PLUGINS.txt
waskr/web/static/flot/README.txt
waskr/web/static/flot/excanvas.js
waskr/web/static/flot/excanvas.min.js
waskr/web/static/flot/jquery.colorhelpers.js
waskr/web/static/flot/jquery.colorhelpers.min.js
waskr/web/static/flot/jquery.flot.crosshair.js
waskr/web/static/flot/jquery.flot.crosshair.min.js
waskr/web/static/flot/jquery.flot.image.js
waskr/web/static/flot/jquery.flot.image.min.js
waskr/web/static/flot/jquery.flot.js
waskr/web/static/flot/jquery.flot.min.js
waskr/web/static/flot/jquery.flot.navigate.js
waskr/web/static/flot/jquery.flot.navigate.min.js
waskr/web/static/flot/jquery.flot.selection.js
waskr/web/static/flot/jquery.flot.selection.min.js
waskr/web/static/flot/jquery.flot.stack.js
waskr/web/static/flot/jquery.flot.stack.min.js
waskr/web/static/flot/jquery.flot.threshold.js
waskr/web/static/flot/jquery.flot.threshold.min.js
waskr/web/static/flot/jquery.js
waskr/web/static/flot/jquery.min.js
waskr/web/static/flot/examples/ajax.html
waskr/web/static/flot/examples/annotating.html
waskr/web/static/flot/examples/arrow-down.gif
waskr/web/static/flot/examples/arrow-left.gif
waskr/web/static/flot/examples/arrow-right.gif
